minibt/SingleAssetFactorOptimizer.py
minibt/__init__.py
minibt/bt.py
minibt/btplot.py
minibt/constant.py
minibt/core.py
minibt/data_enhancement.py
minibt/extendoptimizer.py
minibt/indicators.py
minibt/logger.py
minibt/loss.py
minibt/muon.py
minibt/order.py
minibt/other.py
minibt/rl_utils.py
minibt/ta.py
minibt/ta_.py
minibt/tradingview.py
minibt/tradingview_.py
minibt/typing_.py
minibt/utils.py
minibt/data/contract.csv
minibt/data/settings.ini
minibt/data/tools.py
minibt/data/tqdata.py
minibt/data/utils.py
minibt/data/test/l2601_60.csv
minibt/data/test/pp2601_60.csv
minibt/data/test/test.csv
minibt/data/test/v2601_300.csv
minibt/data/test/v2601_60.csv
minibt/elegantrl/__init__.py
minibt/elegantrl/agents/AgentBase.py
minibt/elegantrl/agents/AgentDQN.py
minibt/elegantrl/agents/AgentEmbedDQN.py
minibt/elegantrl/agents/AgentPPO.py
minibt/elegantrl/agents/AgentPPO_.py
minibt/elegantrl/agents/AgentSAC.py
minibt/elegantrl/agents/AgentTD3.py
minibt/elegantrl/agents/MAgentMADDPG.py
minibt/elegantrl/agents/MAgentMAPPO.py
minibt/elegantrl/agents/MAgentQMix.py
minibt/elegantrl/agents/MAgentVDN.py
minibt/elegantrl/agents/__init__.py
minibt/elegantrl/agents/embedDQN.py
minibt/elegantrl/envs/CustomGymEnv.py
minibt/elegantrl/envs/PlanIsaacGymEnv.py
minibt/elegantrl/envs/PointChasingEnv.py
minibt/elegantrl/envs/StockTradingEnv.py
minibt/elegantrl/envs/__init__.py
minibt/elegantrl/train/__init__.py
minibt/elegantrl/train/config.py
minibt/elegantrl/train/evaluator.py
minibt/elegantrl/train/replay_buffer.py
minibt/elegantrl/train/run.py
minibt/liveplot/account_info
minibt/liveplot/autoscale_cb.js
minibt/liveplot/autoscale_x.js
minibt/liveplot/id
minibt/liveplot/init_datas
minibt/liveplot/live_plot.py
minibt/liveplot/manual_update
minibt/liveplot/pause_status
minibt/liveplot/strategys
minibt/liveplot/trade_datas
minibt/liveplot/update_datas
minibt/liveplot/replay/account_info
minibt/liveplot/replay/id
minibt/liveplot/replay/init_datas
minibt/liveplot/replay/pause_status
minibt-1.1.8.dist-info/licenses/LICENSE
minibt-1.1.8.dist-info/METADATA
minibt-1.1.8.dist-info/WHEEL
minibt-1.1.8.dist-info/top_level.txt
minibt-1.1.8.dist-info/RECORD
