Metadata-Version: 2.4
Name: minibt
Version: 1.1.8
Summary: 一站式量化交易策略开发库，简化从策略搭建到实盘交易的全流程
Author-email: owen <407841129@qq.com>
License: MIT
Project-URL: Homepage, https://github.com/MiniBtMaster/minibt
Project-URL: Documentation, https://www.minibt.cn/
Classifier: Programming Language :: Python :: 3
Classifier: Programming Language :: Python :: 3.8
Classifier: Programming Language :: Python :: 3.9
Classifier: Programming Language :: Python :: 3.10
Classifier: Operating System :: OS Independent
Classifier: Intended Audience :: Developers
Classifier: Intended Audience :: Financial and Insurance Industry
Classifier: Topic :: Software Development :: Libraries :: Python Modules
Classifier: Topic :: Office/Business :: Financial :: Investment
Requires-Python: >=3.8
License-File: LICENSE
Requires-Dist: numpy<=1.26.0,>=1.21.0
Requires-Dist: pandas<2.4.0,>=1.4.0
Requires-Dist: pandas-ta>=0.3.14b0
Requires-Dist: numpy-ext>=0.9.9
Requires-Dist: TA-Lib>=0.4.24
Requires-Dist: finta>=1.3
Requires-Dist: quantstats>=0.0.62
Requires-Dist: statsmodels>=0.13.5
Requires-Dist: scipy<1.13.2,>=1.7.0
Requires-Dist: arch>=7.2.0
Requires-Dist: pykalman>=0.10.1
Requires-Dist: tulipy>=0.4.0
Requires-Dist: tqsdk>=3.4.10
Requires-Dist: bokeh>=3.3.0
Requires-Dist: rich>=13.0.0
Requires-Dist: addict>=2.4.0
Requires-Dist: cachetools>=5.3.0
Requires-Dist: retrying>=1.3.4
Requires-Dist: psutil>=5.9.4
Requires-Dist: iteration-utilities>=0.11.0
Requires-Dist: joblib>=1.2.0
Requires-Dist: colorlog>=6.7.0
Requires-Dist: typing-extensions>=4.12.2
Requires-Dist: optuna>=3.4.0
Requires-Dist: deap>=1.4.1
Requires-Dist: torch>=1.13.1
Requires-Dist: torchcontrib>=0.0.2
Dynamic: license-file
